trsproc/__init__.py
trsproc/__main__.py
trsproc/parser.py
trsproc/utils.py
trsproc-2.0.0.dist-info/LICENSE
trsproc-2.0.0.dist-info/METADATA
trsproc-2.0.0.dist-info/WHEEL
trsproc-2.0.0.dist-info/entry_points.txt
trsproc-2.0.0.dist-info/top_level.txt
trsproc-2.0.0.dist-info/RECORD
