Metadata-Version: 2.1
Name: trsproc
Version: 2.0.0
Summary: A Python library to process Transcriber TRS files
Author-email: Gabriele Chingoli <gabriele@elda.org>
License: MIT License
Project-URL: Homepage, https://github.com/ELDAELRA/trsproc
Keywords: python,transcriber,trs,transcription,textgrid,nlp
Classifier: License :: OSI Approved :: MIT License
Classifier: Programming Language :: Python :: 3
Classifier: Operating System :: OS Independent
Requires-Python: >=3.6
License-File: LICENSE
Requires-Dist: praat-parselmouth
Requires-Dist: praat-textgrids
Requires-Dist: rich
Requires-Dist: tomli ; python_version < "3.11"
